sensirion_shdlc_driver/__init__.py
sensirion_shdlc_driver/command.py
sensirion_shdlc_driver/connection.py
sensirion_shdlc_driver/device.py
sensirion_shdlc_driver/device_base.py
sensirion_shdlc_driver/errors.py
sensirion_shdlc_driver/firmware_image.py
sensirion_shdlc_driver/firmware_update.py
sensirion_shdlc_driver/port.py
sensirion_shdlc_driver/serial_frame_builder.py
sensirion_shdlc_driver/types.py
sensirion_shdlc_driver/version.py
sensirion_shdlc_driver/commands/__init__.py
sensirion_shdlc_driver/commands/baudrate.py
sensirion_shdlc_driver/commands/bootloader.py
sensirion_shdlc_driver/commands/device_info.py
sensirion_shdlc_driver/commands/device_reset.py
sensirion_shdlc_driver/commands/device_version.py
sensirion_shdlc_driver/commands/error_state.py
sensirion_shdlc_driver/commands/factory_reset.py
sensirion_shdlc_driver/commands/reply_delay.py
sensirion_shdlc_driver/commands/slave_address.py
sensirion_shdlc_driver/commands/system_up_time.py
sensirion_shdlc_driver-0.1.5.dist-info/LICENSE
sensirion_shdlc_driver-0.1.5.dist-info/METADATA
sensirion_shdlc_driver-0.1.5.dist-info/WHEEL
sensirion_shdlc_driver-0.1.5.dist-info/top_level.txt
sensirion_shdlc_driver-0.1.5.dist-info/RECORD
